{
  "name": "GymTracker",
  "subtitle": "Musculation & suivi de progression",
  "description": "Source AltStore pour la dernière version de GymTracker.",
  "iconURL": "https://raw.githubusercontent.com/Kyrinnx/GymTracker/main/AltStoreSource/icon.png",
  "headerURL": "https://raw.githubusercontent.com/Kyrinnx/GymTracker/main/AltStoreSource/header.png",
  "website": "https://github.com/Kyrinnx/GymTracker",
  "tintColor": "#FF6B35",
  "featuredApps": [
    "com.gymtracker.app"
  ],
  "apps": [
    {
      "name": "GymTracker",
      "bundleIdentifier": "com.gymtracker.app",
      "developerName": "Kyrinnx",
      "subtitle": "Musculation & suivi de progression",
      "localizedDescription": "Suis tes séances de musculation et ta progression. Records personnels, poids, programmes personnalisés. Tout en local, données 100% privées.",
      "iconURL": "https://raw.githubusercontent.com/Kyrinnx/GymTracker/main/AltStoreSource/icon.png",
      "tintColor": "#FF6B35",
      "category": "lifestyle",
      "screenshotURLs": [],
      "versions": [
        {
          "version": "1.6.0",
          "date": "2026-04-12",
          "localizedDescription": "Import IA multi-séances, bibliothèque de programmes",
          "downloadURL": "https://github.com/Kyrinnx/GymTracker/releases/download/v1.6.0/GymTracker.ipa",
          "size": 2380188,
          "minOSVersion": "17.0"
        },
        {
          "version": "1.5.0",
          "date": "2026-04-12",
          "localizedDescription": "Bibliothèque de 14 programmes, duplication, sauvegarde de séance",
          "downloadURL": "https://github.com/Kyrinnx/GymTracker/releases/download/v1.5.0/GymTracker.ipa",
          "size": 2359013,
          "minOSVersion": "17.0"
        },
        {
          "version": "1.4.0",
          "date": "2026-04-12",
          "localizedDescription": "iCloud obligatoire, création de programmes, import IA",
          "downloadURL": "https://github.com/Kyrinnx/GymTracker/releases/download/v1.4.0/GymTracker.ipa",
          "size": 2331697,
          "minOSVersion": "17.0"
        },
        {
          "version": "1.3.0",
          "date": "2026-04-12",
          "localizedDescription": "Nettoyage du repo, fix HealthKit, nouveau bundle ID",
          "downloadURL": "https://github.com/Kyrinnx/GymTracker/releases/download/v1.3.0/GymTracker.ipa",
          "size": 2204285,
          "minOSVersion": "17.0"
        },
        {
          "version": "1.2.0",
          "date": "2026-04-12",
          "localizedDescription": "Restauration de sauvegarde au premier lancement",
          "downloadURL": "https://github.com/Kyrinnx/GymTracker/releases/download/v1.2.0/GymTracker.ipa",
          "size": 2203657,
          "minOSVersion": "17.0"
        },
        {
          "version": "1.1.0",
          "date": "2026-04-12",
          "localizedDescription": "HealthKit + amélioration sauvegardes iCloud",
          "downloadURL": "https://github.com/Kyrinnx/GymTracker/releases/download/v1.1.0/GymTracker.ipa",
          "size": 2174473,
          "minOSVersion": "17.0"
        },
        {
          "version": "1.0.0",
          "date": "2026-04-12",
          "localizedDescription": "Première version — musculation, nutrition, jeûne, HealthKit",
          "downloadURL": "https://github.com/Kyrinnx/GymTracker/releases/download/v1.0.0/GymTracker.ipa",
          "size": 2161806,
          "minOSVersion": "17.0"
        }
      ],
      "appPermissions": {
        "entitlements": [],
        "privacy": []
      }
    }
  ],
  "news": []
}